MANIFEST.in
license.txt
setup.cfg
setup.py
lighting_fdd/Hard_Fault.py
lighting_fdd/Schedule.py
lighting_fdd/__init__.py
lighting_fdd/hard_fault_checks.py
lighting_fdd/lighting_fdd.py
lighting_fdd/load_analysis.py
lighting_fdd/optimization_checks.py
lighting_fdd/recent_switch_override.py
lighting_fdd/relay_schedule_mismatches.py
lighting_fdd/schedule_analysis.py
lighting_fdd/soft_fault_checks.py
lighting_fdd/suggested_override_timeout_changes.py
lighting_fdd/suggested_schedule_changes.py
lighting_fdd/system_fault_checks.py
lighting_fdd/util.py
lighting_fdd.egg-info/PKG-INFO
lighting_fdd.egg-info/SOURCES.txt
lighting_fdd.egg-info/dependency_links.txt
lighting_fdd.egg-info/requires.txt
lighting_fdd.egg-info/top_level.txt