Metadata-Version: 1.0
Name: lighting-fdd
Version: 0.1.0
Summary: A set of tools for lighting fault detection and diagnosis.
Home-page: https://bitbucket.org/berkeleylab/eetd-tn-lighting/src/modules/lighting_fdd
Author: Lawrence Berkeley National Laboratory
Author-email: UNKNOWN
License: revised BSD
Platform: UNKNOWN
